AUTHORS.md
LICENSE.md
sqlalchemy_dataflex/.DS_Store
sqlalchemy_dataflex/__init__.py
sqlalchemy_dataflex/base.py
sqlalchemy_dataflex/pyodbc.py
sqlalchemy_dataflex/requirements.py
sqlalchemy_dataflex-0.1.5.dist-info/entry_points.txt
sqlalchemy_dataflex-0.1.5.dist-info/LICENSE.md
sqlalchemy_dataflex-0.1.5.dist-info/WHEEL
sqlalchemy_dataflex-0.1.5.dist-info/METADATA
sqlalchemy_dataflex-0.1.5.dist-info/RECORD
