Metadata-Version: 2.1
Name: sqlalchemy-dataflex
Version: 0.1.5
Summary: A SQLAlchemy dialect for DataFlex flat-file databases.
Home-page: https://pypi.org/project/sqlalchemy-dataflex
License: AGPL-3.0-or-later
Keywords: sqlalchemy,dataflex,odbc,flexodbc,dialect
Author: Pawn Payment Solutions
Author-email: support@pawn-pay.com
Maintainer: Mark S.
Maintainer-email: mark@pawn-pay.com
Requires-Python: >=3.9,<4.0
Classifier: Development Status :: 4 - Beta
Classifier: Intended Audience :: Developers
Classifier: License :: OSI Approved :: GNU Affero General Public License v3 or later (AGPLv3+)
Classifier: Natural Language :: English
Classifier: Operating System :: Microsoft
Classifier: Operating System :: Microsoft :: Windows
Classifier: Operating System :: Microsoft :: Windows :: Windows 10
Classifier: Operating System :: Microsoft :: Windows :: Windows 7
Classifier: Operating System :: Microsoft :: Windows :: Windows 8
Classifier: Operating System :: Microsoft :: Windows :: Windows Server 2008
Classifier: Programming Language :: Python
Classifier: Programming Language :: Python :: 3
Classifier: Programming Language :: Python :: 3.7
Classifier: Programming Language :: Python :: 3.8
Classifier: Programming Language :: Python :: 3.9
Classifier: Topic :: Database
Classifier: Topic :: Database :: Database Engines/Servers
Classifier: Topic :: Office/Business
Classifier: Topic :: Other/Nonlisted Topic
Requires-Dist: SQLAlchemy
Requires-Dist: pyodbc
Requires-Dist: python-dateutil
Project-URL: Documentation, https://sqlalchemy-dataflex.readthedocs.io
Project-URL: Repository, https://github.com/the-wondersmith/sqlalchemy-dataflex.git
